cirbreak
test
