Metadata-Version: 2.1
Name: cirbreak
Version: 0.1.2
Summary: A Python library implementing a circuit breaker pattern
Home-page: https://github.com/mario-barrientos-dev/cirbreak
Author: Mario Alfonso Barrientos Benavides
Author-email: mariobarrientos0303@gmail.com
Classifier: Programming Language :: Python :: 3
Classifier: License :: OSI Approved :: MIT License
Classifier: Operating System :: OS Independent
Requires-Python: >=3.6
License-File: LICENSE.txt
